open_recall/__init__.py
open_recall/__main__.py
open_recall/app.py
open_recall/cli.py
open_recall/config.json
open_recall/main.py
open_recall/settings.json
open_recall/alembic/README
open_recall/alembic/env.py
open_recall/alembic/script.py.mako
open_recall/alembic/versions/176b845f3f94_initial_migration.py
open_recall/static/favicon.ico
open_recall/static/css/bootstrap-icons.css
open_recall/static/css/bootstrap.min.css
open_recall/static/css/styles.css
open_recall/static/css/fonts/bootstrap-icons.woff
open_recall/static/css/fonts/bootstrap-icons.woff2
open_recall/static/images/icon.icns
open_recall/static/images/icon.ico
open_recall/static/images/icon.png
open_recall/static/images/logo.png
open_recall/static/js/App.js
open_recall/static/js/components/DeleteScreenshotsPanel.js
open_recall/static/js/components/FilterPanel.js
open_recall/static/js/components/ScreenshotGrid.js
open_recall/static/js/components/ScreenshotModal.js
open_recall/static/js/components/SettingsPanel.js
open_recall/static/js/components/TagManager.js
open_recall/static/js/libs/babel.min.js
open_recall/static/js/libs/bootstrap.bundle.min.js
open_recall/static/js/libs/moment-with-locales.min.js
open_recall/static/js/libs/react-dom.production.min.js
open_recall/static/js/libs/react.production.min.js
open_recall/templates/index.html
open_recall/utils/__init__.py
open_recall/utils/ocr_utils.py
open_recall/utils/schemas.py
open_recall/utils/screenshot_utils.py
open_recall/utils/settings.py
open_recall/utils/summarization.py
open_recall/utils/db_utils/__init__.py
open_recall/utils/db_utils/base.py
open_recall/utils/db_utils/crud.py
open_recall/utils/db_utils/models.py
open_recall_cli-1.0.9.dist-info/LICENSE
open_recall_cli-1.0.9.dist-info/METADATA
open_recall_cli-1.0.9.dist-info/WHEEL
open_recall_cli-1.0.9.dist-info/entry_points.txt
open_recall_cli-1.0.9.dist-info/top_level.txt
open_recall_cli-1.0.9.dist-info/RECORD
