Metadata-Version: 2.2
Name: open_recall_cli
Version: 1.0.9
Summary: Find and analyze anything you've seen on your PC
Author-email: "Eng. Elias Owis" <elias@engelias.website>
License: Copyright (c) 2025 Eng. Elias Owis
Project-URL: Homepage, https://github.com/Eng-Elias/Open_Recall
Project-URL: Bug Tracker, https://github.com/Eng-Elias/Open_Recall/issues
Classifier: Development Status :: 4 - Beta
Classifier: Operating System :: OS Independent
Classifier: Programming Language :: Python :: 3
Classifier: Programming Language :: Python :: 3.11
Requires-Python: >=3.11
License-File: LICENSE
Requires-Dist: fastapi<0.116.0,>=0.95.0
Requires-Dist: uvicorn<0.35.0,>=0.21.1
Requires-Dist: jinja2<3.2.0,>=3.1.2
Requires-Dist: SQLAlchemy<2.1.0,>=2.0.7
Requires-Dist: pillow<12.0.0,>=9.5.0
Requires-Dist: mss<11.0.0,>=9.0.1
Requires-Dist: psutil<7.0.0,>=5.9.0
Requires-Dist: python-multipart>=0.0.20
Requires-Dist: alembic<1.15.0,>=1.10.2
Requires-Dist: toga<0.5.0,>=0.4.0
Requires-Dist: requests<2.33.0,>=2.28.0
Requires-Dist: transformers<4.50.0,>=4.49.0
Requires-Dist: numpy<2.0.0,>=1.26.0
Requires-Dist: python-doctr<0.12.0,>=0.6.0
Requires-Dist: torch<2.7.0,>=2.6.0
Requires-Dist: torchvision<0.22.0,>=0.21.0
